{
  "featuredData": [
    {
      "id": 1,
      "title": "Giảm giá lên đến 30%",
      "image": "sinhnhat.jpg",
      "description": "Chi tiết giảm giá 30%."
    },
    {
      "id": 2,
      "title": "Ẩm thực hạng thương gia",
      "image": "doan.jpg",
      "description": "Thưởng thức ẩm thực đẳng cấp."
    },
    {
      "id": 3,
      "title": "Trải nghiệm khách sạn 5 sao",
      "image": "hanhli.jpg",
      "description": "Chi tiết trải nghiệm khách sạn."
    }
  ],
  "newsData": [
    {
      "id": "1",
      "title": "Ưu đãi tháng này",
      "content": "Chi tiết về ưu đãi đặc biệt khi đặt phòng trước 31/12/2024."
    },
    {
      "id": "2",
      "title": "Hướng dẫn du lịch",
      "content": "Chi tiết các địa điểm nổi tiếng cùng dịch vụ cao cấp."
    },
    {
      "id": "3",
      "title": "Tin tức nội bộ",
      "content": "Chi tiết về khách hàng thứ 1 triệu của chúng tôi!"
    }
  ]
}
